Metadata-Version: 2.1
Name: descriptive-analysis-beginner
Version: 0.1
Summary: Este paquete permite generar un analisis descriptivo con estadisticos y visualizaciones de manera sencilla.
Home-page: https://github.com/nagorebermeosolo/descriptive_analysis_beginner
Download-URL: https://github.com/nagorebermeosolo/descriptive_analysis_beginner/archive/refs/tags/0.1.tar.gz
Author: Nagore Bermeosolo y Ainhoa paredes
Author-email: nagore.bermeosolo@alumni.mondragon.edu
License: MIT
Keywords: Descriptive Analysis,Statistics,EDA
Platform: UNKNOWN
Classifier: Development Status :: 3 - Alpha
Classifier: Intended Audience :: Developers
Classifier: Topic :: Software Development :: Build Tools
Classifier: License :: OSI Approved :: MIT License
Classifier: Programming Language :: Python :: 3.9
License-File: LICENSE.txt
